{
  "schemaVersion": 1,
  "id": "variant_bookshelves",
  "version": "${version}",

  "name": "Variant Bookshelves",
  "description": "Bookshelves for all wood variants",
  "authors": [
    "Xanthian"
  ],

  "license": "CC0-1.0",
  "icon": "assets/variant_bookshelves/icon.png",

  "environment": "*",
  "entrypoints": {
    "main": [
      "net.xanthian.variant_bookshelves.Initialise"
    ]
  },
  "mixins": [
    "variant_bookshelves.mixins.json"
  ],

  "depends": {
    "fabricloader": ">=0.14.6",
    "fabric": "*",
    "minecraft": "~1.19",
    "java": ">=17"
  }
}
